thousandeyes_sdk/endpoint_instant_tests/__init__.py
thousandeyes_sdk/endpoint_instant_tests/py.typed
thousandeyes_sdk/endpoint_instant_tests/api/__init__.py
thousandeyes_sdk/endpoint_instant_tests/api/agent_to_server_endpoint_instant_scheduled_tests_api.py
thousandeyes_sdk/endpoint_instant_tests/api/http_server_endpoint_instant_scheduled_tests_api.py
thousandeyes_sdk/endpoint_instant_tests/api/run_endpoint_instant_scheduled_tests_api.py
thousandeyes_sdk/endpoint_instant_tests/models/__init__.py
thousandeyes_sdk/endpoint_instant_tests/models/endpoint_agent_labels_selector_config.py
thousandeyes_sdk/endpoint_instant_tests/models/endpoint_agent_selector_config.py
thousandeyes_sdk/endpoint_instant_tests/models/endpoint_agent_to_server_instant_test.py
thousandeyes_sdk/endpoint_instant_tests/models/endpoint_agent_to_server_test.py
thousandeyes_sdk/endpoint_instant_tests/models/endpoint_all_agents_selector_config.py
thousandeyes_sdk/endpoint_instant_tests/models/endpoint_http_server_base_test.py
thousandeyes_sdk/endpoint_instant_tests/models/endpoint_http_server_instant_test.py
thousandeyes_sdk/endpoint_instant_tests/models/endpoint_http_server_test.py
thousandeyes_sdk/endpoint_instant_tests/models/endpoint_instant_test.py
thousandeyes_sdk/endpoint_instant_tests/models/endpoint_ip_version_in.py
thousandeyes_sdk/endpoint_instant_tests/models/endpoint_run_scheduled_instant_test_result.py
thousandeyes_sdk/endpoint_instant_tests/models/endpoint_scheduled_test_type.py
thousandeyes_sdk/endpoint_instant_tests/models/endpoint_specific_agents_selector_config.py
thousandeyes_sdk/endpoint_instant_tests/models/endpoint_test.py
thousandeyes_sdk/endpoint_instant_tests/models/endpoint_test_agent_selector_type.py
thousandeyes_sdk/endpoint_instant_tests/models/endpoint_test_auth_type.py
thousandeyes_sdk/endpoint_instant_tests/models/endpoint_test_links.py
thousandeyes_sdk/endpoint_instant_tests/models/endpoint_test_protocol.py
thousandeyes_sdk_endpoint_instant_tests-2.23.0.dist-info/licenses/LICENSE
thousandeyes_sdk_endpoint_instant_tests-2.23.0.dist-info/licenses/NOTICE
thousandeyes_sdk_endpoint_instant_tests-2.23.0.dist-info/METADATA
thousandeyes_sdk_endpoint_instant_tests-2.23.0.dist-info/WHEEL
thousandeyes_sdk_endpoint_instant_tests-2.23.0.dist-info/top_level.txt
thousandeyes_sdk_endpoint_instant_tests-2.23.0.dist-info/RECORD
